[
  {
    "name": "Monty",
    "description": "Simple interpreter for Monty ByteCodes",
    "url": null,
    "github_url": "https://github.com/Barry-dE/monty",
    "image": "monty.png",
    "code": "Code",
    "alt": "A picture of the monty repo"
  },

  {
    "name": "OpenSauced",
    "description": "OpenSauced provides guidance for new contributors to find their next contribution. Our approach towards onboarding offers a way to track contributions through a GitHub-powered dashboard.",
    "url": "https://docs.opensauced.pizza/",
    "github_url": null,
    "image": "SaucedOpen.png",
    "code": null,
    "status": "Contributor",
    "alt": "OpenSauced"
  }
]
